README.md
setup.cfg
setup.py
face_classification/__init__.py
face_classification/face_classifier.py
face_classification/train_model.py
face_classifier.egg-info/PKG-INFO
face_classifier.egg-info/SOURCES.txt
face_classifier.egg-info/dependency_links.txt
face_classifier.egg-info/not-zip-safe
face_classifier.egg-info/requires.txt
face_classifier.egg-info/top_level.txt