Metadata-Version: 1.0
Name: face-classifier
Version: 0.0.1
Summary: Train and classifiy faces from images using deep learning. https://gitlab.lftechnology.com/leapfrogai/face-classification/
Home-page: UNKNOWN
Author: Leapfrog Technology INC
Author-email: bipinkc@lftechnology.com
License: Apache License 2.0
Platform: UNKNOWN
